rtk_mult_clf/__init__.py
rtk_mult_clf/datamodules/__init__.py
rtk_mult_clf/datamodules/datamodule_sklearn.py
rtk_mult_clf/features/__init__.py
rtk_mult_clf/features/transformers.py
rtk_mult_clf/metrics.py
rtk_mult_clf/models/__init__.py
rtk_mult_clf/models/sklearn_model.py
rtk_mult_clf/predictor/__init__.py
rtk_mult_clf/predictor/engine.py
rtk_mult_clf/testing_pipeline_sklearn.py
rtk_mult_clf/training_pipeline_sklearn.py
rtk_mult_clf/utils/__init__.py
rtk_mult_clf-0.1.0.dist-info/WHEEL
rtk_mult_clf-0.1.0.dist-info/METADATA
rtk_mult_clf-0.1.0.dist-info/RECORD
