Metadata-Version: 2.1
Name: rtk-mult-clf
Version: 0.1.0
Summary: 
Author: exotol
Author-email: artem.bardakov@gmail.com
Requires-Python: >=3.9,<4.0
Classifier: Programming Language :: Python :: 3
Classifier: Programming Language :: Python :: 3.10
Classifier: Programming Language :: Python :: 3.9
Requires-Dist: catboost (>=1.0.6,<2.0.0)
Requires-Dist: dvc[gdrive] (>=2.11.0,<3.0.0)
Requires-Dist: hydra-colorlog (>=1.2.0,<2.0.0)
Requires-Dist: hydra-core (>=1.2.0,<2.0.0)
Requires-Dist: numpy (>=1.22.4,<2.0.0)
Requires-Dist: openpyxl (>=3.0.10,<4.0.0)
Requires-Dist: pandas (>=1.4.2,<2.0.0)
Requires-Dist: python-dotenv (>=0.20.0,<0.21.0)
Requires-Dist: pytorch-lightning (>=1.6.4,<2.0.0)
Requires-Dist: razdel (>=0.5.0,<0.6.0)
Requires-Dist: rich (>=12.4.4,<13.0.0)
Requires-Dist: scikit-learn (>=1.1.1,<2.0.0)
Requires-Dist: sentence-transformers (>=2.2.0,<3.0.0)
Requires-Dist: torch (>=1.11.0,<2.0.0)
Requires-Dist: tqdm (>=4.64.0,<5.0.0)
Requires-Dist: wandb (>=0.12.18,<0.13.0)
